aviationdata/__init__.py
aviationdata/aircraft/__init__.py
aviationdata/aircraft/performancetakeoff.py
aviationdata/aircraft/weightbalance.py
aviationdata/blocks/__init__.py
aviationdata/blocks/block.py
aviationdata/blocks/blockcloud.py
aviationdata/blocks/blockforcast.py
aviationdata/blocks/blockpressure.py
aviationdata/blocks/blockrunway.py
aviationdata/blocks/blockrunwayview.py
aviationdata/blocks/blocktemperature.py
aviationdata/blocks/blocktime.py
aviationdata/blocks/blocktrend.py
aviationdata/blocks/blockview.py
aviationdata/blocks/blockweather.py
aviationdata/blocks/blockwind.py
aviationdata/navigation/__init__.py
aviationdata/navigation/kml.py
aviationdata/presenter/__init__.py
aviationdata/presenter/humanpresenter.py
aviationdata/presenter/jsonpresenter.py
aviationdata/receiver/__init__.py
aviationdata/receiver/airportreceiver.py
aviationdata/receiver/hbaircraftreceiver.py
aviationdata/receiver/metarreceiver.py
aviationdata/receiver/tafreceiver.py
python_aviationdata-0.0.11.dist-info/DESCRIPTION.rst
python_aviationdata-0.0.11.dist-info/METADATA
python_aviationdata-0.0.11.dist-info/metadata.json
python_aviationdata-0.0.11.dist-info/RECORD
python_aviationdata-0.0.11.dist-info/top_level.txt
python_aviationdata-0.0.11.dist-info/WHEEL
