Metadata-Version: 2.0
Name: python-aviationdata
Version: 0.0.11
Summary: A library to retrieve aviation relevant data
Home-page: https://github.com/tspycher/python-aviationdata
Author: Thomas Spycher
Author-email: me@tspycher.com
License: MIT
Keywords: aviation metar taf gafor meteo dabs switzerland
Platform: UNKNOWN
Classifier: Development Status :: 3 - Alpha
Classifier: Intended Audience :: Developers
Classifier: License :: OSI Approved :: MIT License
Classifier: Programming Language :: Python :: 2
Classifier: Programming Language :: Python :: 2.6
Classifier: Programming Language :: Python :: 2.7
Requires-Dist: requests
